sdkgen/__init__.py
sdkgen/access_token.py
sdkgen/authenticator.py
sdkgen/client_abstract.py
sdkgen/credentials.py
sdkgen/exceptions.py
sdkgen/parser.py
sdkgen/token_store.py
sdkgen_client-2.0.2.dist-info/LICENSE
sdkgen_client-2.0.2.dist-info/METADATA
sdkgen_client-2.0.2.dist-info/WHEEL
sdkgen_client-2.0.2.dist-info/top_level.txt
sdkgen_client-2.0.2.dist-info/RECORD
