Metadata-Version: 2.2
Name: sdkgen-client
Version: 2.0.2
Summary: SDKgen is a powerful code generator to automatically build client SDKs for your REST API
Author-email: Christoph Kappestein <christoph.kappestein@gmail.com>
License: MIT
Project-URL: Homepage, https://github.com/apioo/sdkgen-python
Project-URL: Issues, https://github.com/apioo/sdkgen-python/issues
Classifier: Programming Language :: Python :: 3
Classifier: License :: OSI Approved :: MIT License
Classifier: Operating System :: OS Independent
Classifier: Topic :: Software Development :: Code Generators
Requires-Python: >=3.8
License-File: LICENSE
Requires-Dist: requests~=2.32.3
Requires-Dist: pydantic~=2.9.2
Provides-Extra: tests
Requires-Dist: pytest; extra == "tests"
